{
  "mirrorVersion": "1",
  "service": "Richopera's Proof Service",
  "periodStart": "2026-06-27T10:00:00.000Z",
  "periodEnd": "2026-06-27T11:00:00.000Z",
  "certificateCount": 0,
  "merkleRoot": "sha256:2fa0ae992ae7a3922d15209b32e1ca948d373b9d3be4c9a06ab0a1727857192e",
  "logJsonHash": "sha256:adda677459fe171bd1c5bf20fe1de8392af12e50f10db6140b83f76ff8ba7582",
  "ots": {
    "file": "log.ots",
    "receiptHash": "sha256:b1708c187969e950d8dbe866d08db7ef4a695b19c92aecc630f5b8cda68caacb",
    "upgraded": true,
    "btcBlockHeight": 955650,
    "btcBlockTime": "2026-06-27T11:31:10.000Z"
  },
  "source": {
    "detailUrl": "https://proof.richopera.cn/logs/2026-06-27/10",
    "logJsonUrl": "https://proof.richopera.cn/api/v1/logs/2026-06-27/10/log.json",
    "otsReceiptUrl": "https://proof.richopera.cn/api/v1/logs/2026-06-27/10/receipt.ots"
  },
  "files": [
    "log.json",
    "log.ots",
    "index.json"
  ]
}
