{
  "mirrorVersion": "1",
  "service": "Richopera's Proof Service",
  "periodStart": "2026-07-23T14:00:00.000Z",
  "periodEnd": "2026-07-23T15:00:00.000Z",
  "certificateCount": 0,
  "merkleRoot": "sha256:2fa0ae992ae7a3922d15209b32e1ca948d373b9d3be4c9a06ab0a1727857192e",
  "logJsonHash": "sha256:c65d2b96b7cc07690ae877fd6f761fedef6201852ad412f181d82824afb49a52",
  "ots": {
    "file": "log.ots",
    "receiptHash": "sha256:ae3fb587109d055905e7d12d5aeb774fdf399ab70a93093b9e05fcc26802ae2c",
    "upgraded": true,
    "btcBlockHeight": 959278,
    "btcBlockTime": "2026-07-23T15:38:33.000Z"
  },
  "source": {
    "detailUrl": "https://proof.richopera.cn/logs/2026-07-23/14",
    "logJsonUrl": "https://proof.richopera.cn/api/v1/logs/2026-07-23/14/log.json",
    "otsReceiptUrl": "https://proof.richopera.cn/api/v1/logs/2026-07-23/14/receipt.ots"
  },
  "files": [
    "log.json",
    "log.ots",
    "index.json"
  ]
}
