{
  "mirrorVersion": "1",
  "service": "Richopera's Proof Service",
  "periodStart": "2026-06-15T15:00:00.000Z",
  "periodEnd": "2026-06-15T16:00:00.000Z",
  "certificateCount": 1,
  "merkleRoot": "sha256:c1bf7a4f451a90a07293f429c5e539b3e50121ace09d5c1d54814bf1f68ade38",
  "logJsonHash": "sha256:f6b159d5f7019b6994ba83db25839e43b47b3855077ff2ad31a678d9eca2e13a",
  "ots": {
    "file": "log.ots",
    "receiptHash": "sha256:9387bca2b468defad3e44cf4db2702876238a99d7ce08e4657cdc7b47ab1cb2e",
    "upgraded": false,
    "btcBlockHeight": null,
    "btcBlockTime": null
  },
  "source": {
    "detailUrl": "https://proof.richopera.cn/logs/2026-06-15/15",
    "logJsonUrl": "https://proof.richopera.cn/api/v1/logs/2026-06-15/15/log.json",
    "otsReceiptUrl": "https://proof.richopera.cn/api/v1/logs/2026-06-15/15/receipt.ots"
  },
  "files": [
    "log.json",
    "log.ots",
    "index.json"
  ]
}
