{
  "mirrorVersion": "1",
  "service": "Richopera's Proof Service",
  "periodStart": "2026-06-09T16:00:00.000Z",
  "periodEnd": "2026-06-09T17:00:00.000Z",
  "certificateCount": 0,
  "merkleRoot": "sha256:2fa0ae992ae7a3922d15209b32e1ca948d373b9d3be4c9a06ab0a1727857192e",
  "logJsonHash": "sha256:f13ca5064f7bfbc238791e86e003c6429dcff855dc3610a036782211d019bb1e",
  "ots": {
    "file": "log.ots",
    "receiptHash": "sha256:b258f2bed7353508a47de953dd9aa09b5c2cc11c5068460acc79f96e3b1e04e8",
    "upgraded": true,
    "btcBlockHeight": 952995,
    "btcBlockTime": "2026-06-09T17:29:28.000Z"
  },
  "source": {
    "detailUrl": "https://proof.richopera.cn/logs/2026-06-09/16",
    "logJsonUrl": "https://proof.richopera.cn/api/v1/logs/2026-06-09/16/log.json",
    "otsReceiptUrl": "https://proof.richopera.cn/api/v1/logs/2026-06-09/16/receipt.ots"
  },
  "files": [
    "log.json",
    "log.ots",
    "index.json"
  ]
}
