{
  "mirrorVersion": "1",
  "service": "Richopera's Proof Service",
  "periodStart": "2026-07-09T13:00:00.000Z",
  "periodEnd": "2026-07-09T14:00:00.000Z",
  "certificateCount": 0,
  "merkleRoot": "sha256:2fa0ae992ae7a3922d15209b32e1ca948d373b9d3be4c9a06ab0a1727857192e",
  "logJsonHash": "sha256:a26c2b9fcc25f030a6abdf22c1dbb526f351840a5f2ce37aef6e0b50226e14fb",
  "ots": {
    "file": "log.ots",
    "receiptHash": "sha256:49bbf34a6717269742d130de6b3bf3e76c7b58466d986808b7c898ed81190927",
    "upgraded": false,
    "btcBlockHeight": null,
    "btcBlockTime": null
  },
  "source": {
    "detailUrl": "https://proof.richopera.cn/logs/2026-07-09/13",
    "logJsonUrl": "https://proof.richopera.cn/api/v1/logs/2026-07-09/13/log.json",
    "otsReceiptUrl": "https://proof.richopera.cn/api/v1/logs/2026-07-09/13/receipt.ots"
  },
  "files": [
    "log.json",
    "log.ots",
    "index.json"
  ]
}
