{
  "mirrorVersion": "1",
  "service": "Richopera's Proof Service",
  "periodStart": "2026-06-02T13:00:00.000Z",
  "periodEnd": "2026-06-02T14:00:00.000Z",
  "certificateCount": 1,
  "merkleRoot": "sha256:12275a827aff3cef8fe400e22994092f087ec8f5c798878cfb8d20a541da27fd",
  "logJsonHash": "sha256:2467e0cb90ef55394f9e374799d01f4921334f6c2cb6c01986516e703b0b776f",
  "ots": {
    "file": "log.ots",
    "receiptHash": "sha256:f453a2d02c499aef013c50ae028ca7667e6aa01a3e49dd40fcbd1fc7a9591f3d",
    "upgraded": true,
    "btcBlockHeight": 952119,
    "btcBlockTime": "2026-06-02T14:49:38.000Z"
  },
  "source": {
    "detailUrl": "https://proof.richopera.cn/logs/2026-06-02/13",
    "logJsonUrl": "https://proof.richopera.cn/api/v1/logs/2026-06-02/13/log.json",
    "otsReceiptUrl": "https://proof.richopera.cn/api/v1/logs/2026-06-02/13/receipt.ots"
  },
  "files": [
    "log.json",
    "log.ots",
    "index.json"
  ]
}
