{
  "mirrorVersion": "1",
  "service": "Richopera's Proof Service",
  "periodStart": "2026-07-23T17:00:00.000Z",
  "periodEnd": "2026-07-23T18:00:00.000Z",
  "certificateCount": 0,
  "merkleRoot": "sha256:2fa0ae992ae7a3922d15209b32e1ca948d373b9d3be4c9a06ab0a1727857192e",
  "logJsonHash": "sha256:371a5115b6db9139f57ed6ae78a22466ec03fe7e90268bb18d7eb20dda34be4f",
  "ots": {
    "file": "log.ots",
    "receiptHash": "sha256:508b19c87523a4d7308e890c9a915ba05f6fa2f066f32de3238bcb37a1079ed2",
    "upgraded": true,
    "btcBlockHeight": 959296,
    "btcBlockTime": "2026-07-23T18:55:08.000Z"
  },
  "source": {
    "detailUrl": "https://proof.richopera.cn/logs/2026-07-23/17",
    "logJsonUrl": "https://proof.richopera.cn/api/v1/logs/2026-07-23/17/log.json",
    "otsReceiptUrl": "https://proof.richopera.cn/api/v1/logs/2026-07-23/17/receipt.ots"
  },
  "files": [
    "log.json",
    "log.ots",
    "index.json"
  ]
}
