{
  "mirrorVersion": "1",
  "service": "Richopera's Proof Service",
  "periodStart": "2026-07-07T22:00:00.000Z",
  "periodEnd": "2026-07-07T23:00:00.000Z",
  "certificateCount": 0,
  "merkleRoot": "sha256:2fa0ae992ae7a3922d15209b32e1ca948d373b9d3be4c9a06ab0a1727857192e",
  "logJsonHash": "sha256:988661119be2ba2476435c1017e5d686d21621403b74482aa4c6132e47905f89",
  "ots": {
    "file": "log.ots",
    "receiptHash": "sha256:89168c288697ce42f707033c9448a26d9ef402ecd90213f9b69fd2ddf6c50770",
    "upgraded": true,
    "btcBlockHeight": 957099,
    "btcBlockTime": "2026-07-07T23:22:24.000Z"
  },
  "source": {
    "detailUrl": "https://proof.richopera.cn/logs/2026-07-07/22",
    "logJsonUrl": "https://proof.richopera.cn/api/v1/logs/2026-07-07/22/log.json",
    "otsReceiptUrl": "https://proof.richopera.cn/api/v1/logs/2026-07-07/22/receipt.ots"
  },
  "files": [
    "log.json",
    "log.ots",
    "index.json"
  ]
}
