{
  "mirrorVersion": "1",
  "service": "Richopera's Proof Service",
  "periodStart": "2026-06-08T09:00:00.000Z",
  "periodEnd": "2026-06-08T10:00:00.000Z",
  "certificateCount": 0,
  "merkleRoot": "sha256:2fa0ae992ae7a3922d15209b32e1ca948d373b9d3be4c9a06ab0a1727857192e",
  "logJsonHash": "sha256:e6d9f69fd8a24b829529cc6dbf369e266ee78b771c2b6f4d6f0d98815880258c",
  "ots": {
    "file": "log.ots",
    "receiptHash": "sha256:9691b10598017434bc553162b87bd5c70666ad1a1199229cb5927951337d1363",
    "upgraded": true,
    "btcBlockHeight": 952838,
    "btcBlockTime": "2026-06-08T10:25:27.000Z"
  },
  "source": {
    "detailUrl": "https://proof.richopera.cn/logs/2026-06-08/09",
    "logJsonUrl": "https://proof.richopera.cn/api/v1/logs/2026-06-08/09/log.json",
    "otsReceiptUrl": "https://proof.richopera.cn/api/v1/logs/2026-06-08/09/receipt.ots"
  },
  "files": [
    "log.json",
    "log.ots",
    "index.json"
  ]
}
