{
  "mirrorVersion": "1",
  "service": "Richopera's Proof Service",
  "periodStart": "2026-07-19T19:00:00.000Z",
  "periodEnd": "2026-07-19T20:00:00.000Z",
  "certificateCount": 0,
  "merkleRoot": "sha256:2fa0ae992ae7a3922d15209b32e1ca948d373b9d3be4c9a06ab0a1727857192e",
  "logJsonHash": "sha256:c9a2d712eec9e840dcf8fd811a6cbb7b12dd441fd9c408d5ba673b911cee0ec3",
  "ots": {
    "file": "log.ots",
    "receiptHash": "sha256:4e0cf2fba6984a9ccfa34801d072c5bd07e4e5cbf708629a8d9515ed9e9a1915",
    "upgraded": true,
    "btcBlockHeight": 958776,
    "btcBlockTime": "2026-07-19T20:11:59.000Z"
  },
  "source": {
    "detailUrl": "https://proof.richopera.cn/logs/2026-07-19/19",
    "logJsonUrl": "https://proof.richopera.cn/api/v1/logs/2026-07-19/19/log.json",
    "otsReceiptUrl": "https://proof.richopera.cn/api/v1/logs/2026-07-19/19/receipt.ots"
  },
  "files": [
    "log.json",
    "log.ots",
    "index.json"
  ]
}
