{
  "mirrorVersion": "1",
  "service": "Richopera's Proof Service",
  "periodStart": "2026-07-10T13:00:00.000Z",
  "periodEnd": "2026-07-10T14:00:00.000Z",
  "certificateCount": 0,
  "merkleRoot": "sha256:2fa0ae992ae7a3922d15209b32e1ca948d373b9d3be4c9a06ab0a1727857192e",
  "logJsonHash": "sha256:201882daf01ede55b26759eeffe04408e1652bcd566cfc8fc4a89b6b0d849c56",
  "ots": {
    "file": "log.ots",
    "receiptHash": "sha256:f123aa68bd0be65343d776dd078c4a6d760e7b3aef5168e8e3e72eee71f4f98e",
    "upgraded": true,
    "btcBlockHeight": 957435,
    "btcBlockTime": "2026-07-10T14:23:07.000Z"
  },
  "source": {
    "detailUrl": "https://proof.richopera.cn/logs/2026-07-10/13",
    "logJsonUrl": "https://proof.richopera.cn/api/v1/logs/2026-07-10/13/log.json",
    "otsReceiptUrl": "https://proof.richopera.cn/api/v1/logs/2026-07-10/13/receipt.ots"
  },
  "files": [
    "log.json",
    "log.ots",
    "index.json"
  ]
}
