{
  "mirrorVersion": "1",
  "service": "Richopera's Proof Service",
  "periodStart": "2026-06-20T00:00:00.000Z",
  "periodEnd": "2026-06-20T01:00:00.000Z",
  "certificateCount": 0,
  "merkleRoot": "sha256:2fa0ae992ae7a3922d15209b32e1ca948d373b9d3be4c9a06ab0a1727857192e",
  "logJsonHash": "sha256:455018be124ca7ceea05506792985a337bcb8014dc8ede872c5cd55e67d59465",
  "ots": {
    "file": "log.ots",
    "receiptHash": "sha256:75aaf18a0d9b9d1974fe93119c5a71f95b957de6682999ade8160f125d1212e7",
    "upgraded": true,
    "btcBlockHeight": 954478,
    "btcBlockTime": "2026-06-20T01:37:02.000Z"
  },
  "source": {
    "detailUrl": "https://proof.richopera.cn/logs/2026-06-20/00",
    "logJsonUrl": "https://proof.richopera.cn/api/v1/logs/2026-06-20/00/log.json",
    "otsReceiptUrl": "https://proof.richopera.cn/api/v1/logs/2026-06-20/00/receipt.ots"
  },
  "files": [
    "log.json",
    "log.ots",
    "index.json"
  ]
}
