{
  "mirrorVersion": "1",
  "service": "Richopera's Proof Service",
  "periodStart": "2026-07-23T01:00:00.000Z",
  "periodEnd": "2026-07-23T02:00:00.000Z",
  "certificateCount": 0,
  "merkleRoot": "sha256:2fa0ae992ae7a3922d15209b32e1ca948d373b9d3be4c9a06ab0a1727857192e",
  "logJsonHash": "sha256:a24c5378cce40f0f9ac1ede12d7378e353d47febdcbe13662b347978f8ca4058",
  "ots": {
    "file": "log.ots",
    "receiptHash": "sha256:3ec19e0fba2ec6992b1a3f7938f1e164d9060aa7fa1a46bfbcb2ee6f6dce8397",
    "upgraded": false,
    "btcBlockHeight": null,
    "btcBlockTime": null
  },
  "source": {
    "detailUrl": "https://proof.richopera.cn/logs/2026-07-23/01",
    "logJsonUrl": "https://proof.richopera.cn/api/v1/logs/2026-07-23/01/log.json",
    "otsReceiptUrl": "https://proof.richopera.cn/api/v1/logs/2026-07-23/01/receipt.ots"
  },
  "files": [
    "log.json",
    "log.ots",
    "index.json"
  ]
}
